{"cameraMode":{"drawMode":0,"name":"Shaded","section":"Shading Mode"},"sceneLighting":true,"audioPlay":false,"sceneViewState":{"m_AlwaysRefresh":false,"showFog":true,"showSkybox":true,"showFlares":true,"showImageEffects":true,"showParticleSystems":true,"showVisualEffectGraphs":true,"m_FxEnabled":true},"in2DMode":false,"pivot":{"x":7.042041778564453,"y":-12.200906753540039,"z":-3.444155693054199},"rotation":{"x":0.45749199390411379,"y":-0.10044576972723007,"z":0.05210210010409355,"w":0.881986677646637},"size":14.800823211669922,"orthographic":false}